project_euler_aid/__init__.py
project_euler_aid/helpers.py
project_euler_aid/project_euler_aid.py
project_euler_aid-1.0.0.dist-info/LICENSE
project_euler_aid-1.0.0.dist-info/METADATA
project_euler_aid-1.0.0.dist-info/WHEEL
project_euler_aid-1.0.0.dist-info/top_level.txt
project_euler_aid-1.0.0.dist-info/RECORD
